<?xml version="1.0" encoding="UTF-8"?>
<?xml-stylesheet href="urn:x-suse:xslt:profiling:docbook50-profile.xsl"
 type="text/xml"
 title="Profiling step"?>
<appendix xmlns="http://docbook.org/ns/docbook" xmlns:xi="http://www.w3.org/2001/XInclude" xmlns:xlink="http://www.w3.org/1999/xlink" xml:base="gnome_docupdates.xml" version="5.0" xml:id="app.gnome.docupdates">
 <title>文档更新</title>
 <info>
  <dm:docmanager xmlns:dm="urn:x-suse:ns:docmanager">
   <dm:bugtracker/>
   <dm:translation>yes</dm:translation>
  </dm:docmanager>
 </info>
 <para>
  本章列出了本文档的内容更改。
 </para>
 <para>
  本手册在以下日期进行了更新：
 </para>

 <itemizedlist>
  <listitem>
   <para>
    <xref linkend="sec.gnome.docupdates.sle12_sp2" xrefstyle="SectTitleOnPage"/>
   </para>
  </listitem>
  <listitem>
   <para>
    <xref linkend="sec.gnome.docupdates.sle12_sp1" xrefstyle="SectTitleOnPage"/>
   </para>
  </listitem>
  <listitem>
   <para>
    <xref linkend="sec.gnome.docupdates.sle12_ga" xrefstyle="SectTitleOnPage"/>
   </para>
  </listitem>
 </itemizedlist>
 <sect1 xml:id="sec.gnome.docupdates.sle12_sp2">
  <title>2016 年 10 月（<phrase role="productname"><phrase os="sled">SUSE Linux Enterprise Desktop</phrase></phrase> 12 SP2 的初始版本）</title>



  <xi:include href="common_docupdates_sp2_i.xml"/>

  <variablelist>
   <varlistentry>
    <term>本指南的更改</term>
    <listitem>
     <itemizedlist>
      <listitem>
       <para>
        本书结构：重新编排并合并了一些章节。
       </para>
      </listitem>
      <listitem>
       <para>
        文档内容从 GNOME 3.10 更新到 GNOME 3.20。只是一些小改动。
       </para>
      </listitem>
      <listitem>
       <para>
        文档中更新了 LibreOffice 5.1。只是一些小改动。(FATE#320521)
       </para>
      </listitem>
     </itemizedlist>
    </listitem>
   </varlistentry>
  </variablelist>
 </sect1>
 <sect1 xml:id="sec.gnome.docupdates.sle12_sp1">
  <title>2015 年 12 月（<phrase role="productname"><phrase os="sled">SUSE Linux Enterprise Desktop</phrase></phrase> 12 SP1 的初始版本）</title>



  <xi:include href="common_docupdates_sp1_i.xml"/>

  <variablelist>
   <varlistentry>
    <term>本指南的更改</term>
    <listitem>
     <itemizedlist>
      <listitem>
       <para>
        更新了 Evolution 文档，以包括有关 Exchange Web 服务支持的内容 (<xref linkend="cha.gnome.evolution"/>)。
       </para>
      </listitem>
      <listitem>
       <para>
        更新了 Firefox 文档，以包括有关 Firefox ESR 38 的内容 (<xref linkend="cha.firefox"/>)。
       </para>
      </listitem>
      <listitem>
       <para>
        更新了 GIMP 文档 (<xref linkend="cha.gimp"/>)。
       </para>
      </listitem>
     </itemizedlist>
    </listitem>
   </varlistentry>
   <varlistentry>
    <term>Bug 修复</term>
    <listitem>
     <itemizedlist>
      <listitem>
       <para>
        修复了称呼 GNOME Shell 仪表板的不一致术语（文档注释中）。
       </para>
      </listitem>
     </itemizedlist>
    </listitem>
   </varlistentry>
  </variablelist>
 </sect1>
 <sect1 xml:id="sec.gnome.docupdates.sle12_ga">
  <title>2014 年 10 月（<phrase role="productname"><phrase os="sled">SUSE Linux Enterprise Desktop</phrase></phrase> 12 的初始版本）</title>

  <para/>



  <xi:include href="common_docupdates_ga_i.xml"/>

  <variablelist>
   <varlistentry>
    <term>本指南的更改</term>
    <listitem>
     <itemizedlist>
      <listitem>
       <para>
        《<citetitle>Application Guide</citetitle>》（应用指南）已合并到本指南中。
       </para>
      </listitem>
      <listitem>
       <para>
        《<citetitle>LibreOffice Quick Start</citetitle>》（LibreOffice 快速入门）已合并到本指南中。
       </para>
      </listitem>
      <listitem>
       <para>
        文档中的 GNOME 2 相关内容已更新为 GNOME 3 相关内容。重要的用户界面有所变动。
       </para>
      </listitem>
     </itemizedlist>
    </listitem>
   </varlistentry>

  </variablelist>
 </sect1>
</appendix>
