<?xml version="1.0" encoding="UTF-8"?>
<variablelist xmlns="http://docbook.org/ns/docbook" xmlns:xi="http://www.w3.org/2001/XInclude" xmlns:xlink="http://www.w3.org/1999/xlink" xml:base="common_docupdates_ga_i.xml" version="5.0">
 <info>
  <dm:docmanager xmlns:dm="urn:x-suse:ns:docmanager">
   <dm:bugtracker/>
   <dm:translation>sì</dm:translation>
  </dm:docmanager>
 </info>
 <varlistentry>
  <term>Generale</term>
  <listitem>
   <itemizedlist>
    <listitem>
     <para>
      Sono stati rimossi la documentazione e tutti i riferimenti relativi a KDE in quanto KDE non viene più fornito.
     </para>
    </listitem>
    <listitem>
     <para>
      Sono stati rimossi tutti i riferimenti a SuSEconfig, che non è più supportato (Fate#100011).
     </para>
    </listitem>
    <listitem>
     <para>
      È stato effettuato il passaggio da System V init a systemd (Fate#310421). Sono state aggiornate le parti della documentazione interessate.
     </para>
    </listitem>
    <listitem>
     <para>
      L'editor di runlevel YaST è cambiato in Gestore dei servizi (Fate#312568). Sono state aggiornate le parti della documentazione interessate.
     </para>
    </listitem>
    <listitem>
     <para>
      Sono stati rimossi tutti i riferimenti al supporto ISDN, in quanto tale supporto è stato rimosso (Fate#314594).
     </para>
    </listitem>
    <listitem>
     <para>
      Sono stati rimossi tutti i riferimenti al modulo DSL YaST in quanto questo non viene più fornito (Fate#316264).
     </para>
    </listitem>
    <listitem>
     <para>
      Sono stati rimossi tutti i riferimenti al modulo Modem YaST in quanto questo non viene più fornito (Fate#316264).
     </para>
    </listitem>
    <listitem>
     <para>
      Btrfs è diventato il file system di default per la partizione radice (Fate#315901). Sono state aggiornate le parti della documentazione interessate.
     </para>
    </listitem>
    <listitem>
     <para>
      <command>dmesg</command> ora fornisce registrazioni dell'orario leggibili dall'uomo in formato simile a <literal>ctime()</literal> (Fate#316056). Sono state aggiornate le parti della documentazione interessate.
     </para>
    </listitem>
    <listitem>
     <para>
      syslog e syslog-ng sono stati sostituiti da rsyslog (Fate#316175). Sono state aggiornate le parti della documentazione interessate.
     </para>
    </listitem>
    <listitem>
     <para>
      Come database relazionale viene ora fornito MariaDB anziché MySQL (Fate#313595). Sono state aggiornate le parti della documentazione interessate.
     </para>
    </listitem>
    <listitem>
     <para>
      I prodotti correlati a SUSE non sono più disponibili da <link xlink:href="http://download.novell.com"/> bensì da <link xlink:href="http://download.suse.com"/>. I collegamenti sono stati modificati di conseguenza.
     </para>
    </listitem>
    <listitem>
     <para>
      Novell Customer Center è stato sostituito da SUSE Customer Center. Sono state aggiornate le parti della documentazione interessate.
     </para>
    </listitem>
    <listitem>
     <para>
      <filename>/var/run</filename> è montato come tmpfs (Fate#303793). Sono state aggiornate le parti della documentazione interessate.
     </para>
    </listitem>
    <listitem>
     <para>
      Le architetture IA64 e x86 non sono più supportate. Sono state aggiornate le parti della documentazione interessate.
     </para>
    </listitem>
    <listitem>
     <para>
      Il metodo tradizionale per configurare la rete con <systemitem>ifconfig</systemitem> è stato sostituito da <systemitem>wicked</systemitem>. Sono state aggiornate le parti della documentazione interessate.
     </para>
    </listitem>
    <listitem>
     <para>
      Molti comandi di networking sono ormai obsoleti e sono stati sostituiti da comandi più recenti (in genere <command>ip</command>). Sono state aggiornate le parti della documentazione interessate.
     </para>
     <simplelist>
      <member><command>arp</command>: <command>ip neighbor</command>
      </member>
      <member><command>  ifconfig</command>: <command>ip addr</command>, <command>ip link</command>
      </member>
      <member><command>  iptunnel</command>: <command>ip tunnel</command>
      </member>
      <member><command>  iwconfig</command>: <command>iw</command>
      </member>
      <member><command>  nameif</command>: <command>ip link</command>, <command>ifrename</command>
      </member>
      <member><command>  netstat</command>: <command>ss</command>, <command>ip route</command>, <command>ip -s link</command>, <command>ip maddr</command>
      </member>
      <member><command>  route</command>: <command>ip route</command>
      </member>
     </simplelist>
    </listitem>
    <listitem>
     <para>
      Numerose piccole correzioni e aggiunte alla documentazione, in base al feedback tecnico.
     </para>
    </listitem>
   </itemizedlist>
  </listitem>
 </varlistentry>
</variablelist>
