<?xml version="1.0" encoding="UTF-8"?>
<legalnotice xmlns="http://docbook.org/ns/docbook" xmlns:xi="http://www.w3.org/2001/XInclude" xmlns:xlink="http://www.w3.org/1999/xlink" xml:base="common_copyright_gfdl.xml" version="5.0">
 <info>
  <dm:docmanager xmlns:dm="urn:x-suse:ns:docmanager">
   <dm:translation>sì</dm:translation>
  </dm:docmanager>
 </info>
 <para>
  Copyright © 2006–
<?dbtimestamp format="Y"?>


  SUSE LLC e collaboratori. Tutti i diritti riservati.
 </para>
 <para>
  L'autorizzazione per la copia, la distribuzione e/o la modifica di questo documento è soggetta ai termini indicati nella licenza GFDL (GNU Free
Documentation License), versione 1.2 oppure, a scelta, 1.3, di cui la presente licenza e le presenti informazioni sul copyright rappresentano la sezione non variabile. Una copia della licenza versione 1.2 è inclusa nella sezione intitolata <quote>GNU Free Documentation License</quote>.
 </para>
 <para>
  Per i marchi di fabbrica SUSE vedere <link xlink:href="http://www.suse.com/company/legal/"/>. Tutti gli altri marchi di fabbrica di terze parti sono proprietà dei rispettivi titolari. I simboli di marchio di fabbrica (®, ™ e così via) indicano i marchi di fabbrica appartenenti a SUSE e alle rispettive affiliate. Gli asterischi (*) indicano i marchi di fabbrica di terze parti.
 </para>
 <para>
  Tutte le informazioni nella presente pubblicazione sono state compilate con la massima attenzione ai dettagli. Ciò, tuttavia, non garantisce una precisione assoluta. SUSE LLC, le rispettive affiliate, gli autori e i traduttori non potranno essere ritenuti responsabili di eventuali errori o delle relative conseguenze.
 </para>
</legalnotice>
