<?xml version="1.0" encoding="UTF-8"?>
<!DOCTYPE authorgroup
[
  <!ENTITY % entities SYSTEM "generic-entities.ent">
    %entities;
]>
<!-- Converted by suse-upgrade version 1.1 -->
<authorgroup xmlns="http://docbook.org/ns/docbook" xmlns:xi="http://www.w3.org/2001/XInclude" xmlns:xlink="http://www.w3.org/1999/xlink" version="5.0">
 <author><personname><firstname>Dmitri</firstname><surname>Popov</surname></personname>
 </author>
 <author><personname><firstname>Nora</firstname><surname>Kořánová</surname></personname> 
 </author>
</authorgroup>
 
