<?xml version="1.0"?>
<!DOCTYPE appendix PUBLIC "-//Novell//DTD NovDoc XML V1.0//EN" "novdocx.dtd"
[
  <!ENTITY % NOVDOC.DEACTIVATE.IDREF "INCLUDE">
  <!ENTITY % entities SYSTEM "entity-decl.ent">
  %entities;
]>
<appendix id="app.vmdp.driver">
 <title>Virtual Machine Drivers</title>
 <para>
  Virtualization allows the consolidation of workloads on newer, more
  powerful, energy-efficient hardware. Paravirtualized operating systems
  such as &productnamereg; and other Linux distributions are aware of the
  underlying virtualization platform, and can therefore interact efficiently
  with it. Unmodified operating systems such as Microsoft Windows* are
  unaware of the virtualization platform and expect to interact directly
  with the hardware. Because this is not possible when consolidating
  servers, the hardware must be emulated for the operating system. Emulation
  can be slow, but it is especially troubling for high-throughput disk and
  network subsystems. Most performance loss occurs in this area.
 </para>
 <para>
  The &sle; Virtual Machine Driver Pack (VMDP) contains 32-bit and 64-bit
  paravirtualized network, bus and block drivers for a number of Microsoft
  Windows operating systems.
  These drivers bring many of the performance advantages of
  paravirtualized operating systems to unmodified operating systems because
  only the paravirtualized device driver (not the rest of the operating
  system) is aware of the virtualization platform. For example, a
  paravirtualized disk device driver appears as a normal, physical disk to
  the operating system. However, the device driver interacts directly with
  the virtualization platform (with no emulation) to efficiently deliver
  disk access, allowing the disk and network subsystems to operate at near
  native speeds in a virtualized environment, without requiring changes to
  existing operating systems.
 </para>
 <para>
  The &slereg; Virtual Machine Driver Pack is available as an add-on product
  for &productname;. For detailed information please refer to
  <ulink
   url="http://www.suse.com/products/vmdriverpack/"/>.
 </para>
 <para>
  Please refer to the Official VMDP Installation Guide for more information.
 </para>
<!-- bg: I have no idea if we still get support for this as an extra
 product. I know that we directly deliver VMDP with the product now, but I
 have no information (although asking) where this is found. Thus commenting
 all of the following information.

 <sect1 id="sec.xen.drivers.subscription">
  <title>Buying a Support Subscription</title>

  <para>
   The customer support you receive for the &sle; Virtual Machine Driver
   Pack is at the same level as your
   <ulink url="http://support.novell.com/linux/sles_support.html">SUSE Linux
   Enterprise support subscription</ulink>. You can choose the following
   levels of support:
  </para>

  <itemizedlist>
   <listitem>
    <para>
     Basic
    </para>
   </listitem>
   <listitem>
    <para>
     Standard
    </para>
   </listitem>
   <listitem>
    <para>
     Priority
    </para>
   </listitem>
  </itemizedlist>

  <para>
   Descriptions of these levels of support and how to buy them are found at
   <ulink
    url="http://www.novell.com/products/server/howtobuy.html">&productname;
   &productnumber; How to Buy</ulink>.
  </para>
 </sect1> -->
<!-- bg: I don't want to describe the installation again.
  <sect1 id="sec.xen.driver.inst">
   <title>Installing the Virtualization Host Server</title>

   <procedure>
    <step>
     <para>
      Install SLES 10 SP1 (see the
      <ulink url="http://www.suse.com/doc/sles10/sles_admin/index.html?page=/documentation/sles10/sles_admin/data/sles_admin.html">
      <citetitle>SLES 10 Installation and Administration Guide</citetitle>
      </ulink>.
     </para>
     <para>
      During the SLES 10 SP1 installation, do the following:
     </para>
     <itemizedlist>
      <listitem>
       <para>
        Install the minimal packages necessary for SLES, including the Xen
        Virtual Machine Host Server package. (For best performance, the host
        server should be running only packages required for virtualization.)
       </para>
      </listitem>
      <listitem>
       <para>
        Turn off the firewall.
       </para>
      </listitem>
      <listitem>
       <para>
        Make sure to use ifup, not Network Manager. To change the
        network configuration method, start &yast; and select
        <menuchoice><guimenu>Network
          Devices</guimenu><guimenu>Network
          Card</guimenu></menuchoice>.
       </para>
      </listitem>
     </itemizedlist>
    </step>
    <step>
     <para>
      Get the latest updates for SLES 10 SP1. Use <guimenu>YaST</guimenu>
      &gt; <guimenu>Software</guimenu> &gt; <guimenu>Online Update</guimenu>
      or click the <guimenu>Software Updater</guimenu> on the taskbar.
     </para>
     <note>
      <para>
       To get updates, you must register with Novell Customer Center.
      </para>
     </note>
    </step>
   </procedure>
  </sect1> -->
<!--
 <sect1 id="sec.xen.drivers.vmdp">
  <title>Loading the Driver Pack</title>

  <procedure>
   <step>
    <para>
     Download the SLES-Virtual-Machine-Driver-Pack-10.iso file to your SLES
     11 virtual machine host server.
    </para>
   </step>
   <step>
    <para>
     Open &yast;.
    </para>
   </step>
   <step>
    <para>
     Select <guimenu>Software</guimenu>, then click <guimenu>Add-on
     Product</guimenu>.
    </para>
   </step>
   <step>
    <para>
     Click <guimenu>Local ISO Image</guimenu>, then click
     <guimenu>Next</guimenu>.
    </para>
    <informalfigure pgwide="0">
     <mediaobject>
      <imageobject role="fo">
       <imagedata fileref="browsetoiso.png" width="35%" format="PNG"/>
      </imageobject>
      <imageobject role="html">
       <imagedata fileref="browsetoiso.png" width="35%" format="png"/>
      </imageobject>
     </mediaobject>
    </informalfigure>
   </step>
   <step>
    <para>
     Browse to the location of the driver pack ISO image you downloaded.
    </para>
   </step>
   <step>
    <para>
     Select the driver pack ISO, then click <guimenu>Open</guimenu>. Click
     <guimenu>OK</guimenu>.
    </para>
   </step>
   <step>
    <para>
     Select <guimenu>Patterns</guimenu> from the <guimenu>Filter</guimenu>
     drop-down list. The drivers are located under Virtual Machine Driver
     Pack.
    </para>
   </step>
   <step>
    <para>
     Select the drivers you want to install, then click
     <guimenu>Accept</guimenu>.
    </para>
   </step>
   <step>
    <para>
     When asked if you want to install more packages, click
     <guimenu>No</guimenu>.
    </para>
    <para>
     The drivers are now on your system in the
     <filename>/opt/novell/vm-driver-pack</filename> directory.
    </para>
   </step>
  </procedure>
 </sect1> -->
<!--
  <sect1 id="sec.xen.driver.security">
   <title>Security Information</title>

   <para>
    There are no known security issues introduced by the device drivers in
    this driver pack; however, you should familiarize yourself with
    potential security issues on
    <ulink url="http://www.xensource.com">XEN</ulink>. We recommend that you
    follow the security recommendations for the operating system you are
    using.
   </para>

   <para>
    These drivers do not contain or use cryptography.
   </para>
  </sect1> -->
<!--
 <xi:include xmlns:xi="http://www.w3.org/2001/XInclude"
   href="xen_susedriversforrh4.xml"></xi:include>
 <xi:include xmlns:xi="http://www.w3.org/2001/XInclude"
   href="xen_susedriversforrh5.xml"></xi:include>
 <xi:include xmlns:xi="http://www.w3.org/2001/XInclude"
   href="xen_susedriversforwindows.xml"></xi:include>
 <xi:include xmlns:xi="http://www.w3.org/2001/XInclude"
  href="xen_susedriversforsles.xml"></xi:include> -->
<!-- bg: Jason Douglas thinks that we should have just one chapter
  about sles. The sles10 section currently is even inaccurate...
  <xi:include xmlns:xi="http://www.w3.org/2001/XInclude"
   href="xen_susedriversforsles9.xml"></xi:include>
  <xi:include xmlns:xi="http://www.w3.org/2001/XInclude"
   href="xen_susedriversforsles10.xml"></xi:include> -->
</appendix>
