<?xml version="1.0" encoding="UTF-8"?>
<sect1 xmlns="http://docbook.org/ns/docbook" xmlns:xi="http://www.w3.org/2001/XInclude" xmlns:xlink="http://www.w3.org/1999/xlink" xml:base="power_preparing.xml" version="5.0" xml:id="cha.power.prep">
 <title>準備</title>

<info>
      <dm:docmanager xmlns:dm="urn:x-suse:ns:docmanager">
        <dm:bugtracker>
          </dm:bugtracker>
        <dm:translation>yes</dm:translation>
      </dm:docmanager>
    </info>
    <indexterm><primary>電源</primary><secondary>準備</secondary></indexterm>

 <para>
  本節說明實際安裝 SUSE Linux Enterprise Server 之前必須執行的準備步驟。安裝程序視所使用的系統而異。請參閱下列文件：
 </para>

 <itemizedlist mark="bullet" spacing="normal">

  <listitem>
   <para>
    若要使用 Kimchi 在執行 IBM PowerKVM 的 IBM PowerLinux 伺服器上進行安裝，請參閱<xref linkend="sec.prep.powerlinux.powerkvm.kimchi"/>。
   </para>
  </listitem>
 </itemizedlist>





 <para>
  如果需要將 SUSE® Linux Enterprise Server 安裝於多個系統或分割區中，建議您建立網路安裝來源。相同來源亦可讓多個系統或分割區同時進行安裝。網路安裝來源組態的詳細資訊，請參閱 <xref linkend="sec.deployment.remoteinst.instserver.sles9"/>。
 </para>

 <para>
  安裝過程可由 VNC 用戶端控制。如需關於 VNC 的詳細資訊，請參閱<xref linkend="sec.deployment.remoteinst.scenario.vncstat"/>。
 </para>

 <para>
  若要加入 <filename>linuxppc-dev</filename> 郵件清單，請使用 <link xlink:href="http://lists.ozlabs.org/listinfo/linuxppc-dev/"/> 中的表單進行註冊。下列連結提供有關安裝維護的內容：
 </para>

 <itemizedlist mark="bullet" spacing="normal">
  <listitem>
   <para>
    <link xlink:href="http://www.suse.com/support/kb/"/> 是非常有效的說明工具，可協助客戶解決問題。當 SUSE 發現可能導致嚴重問題的特殊案例，就會發表相關的文章。使用如 POWER 或 PowerKVM 等關鍵字搜尋入口網站。
   </para>
  </listitem>
  <listitem>
   <para>
    可於 <link xlink:href="http://www.suse.com/support/security/"/> 中尋找安全性警告。SUSE 亦維護兩份安全性相關的郵寄清單，所有人均可訂閱。
   </para>
   <itemizedlist mark="bullet" spacing="normal">
    <listitem>
     <para>
      <literal>suse-security</literal> — 與 Linux 和 SUSE 相關的一般安全性討論。會將所有 SUSE Linux Enterprise Server 的安全性警告寄給此清單上的收件人。
     </para>
    </listitem>
    <listitem>
     <para>
      <literal>suse-security-announce</literal> — 專門提供安全性警告的 SUSE 郵寄清單。
     </para>
    </listitem>
   </itemizedlist>
  </listitem>
 </itemizedlist>

 <xi:include href="power_powerlinux_powerkvm.xml"/>

 <sect2 xml:id="sec.prep.powerlinux.powerkvm.virt-install">
  <title>使用 <command>virt-install</command> 在執行 IBM PowerKVM 的 IBM PowerLinux 伺服器上進行安裝</title>
  <para>
   或者，如果您需要在 IBM PowerLinux 伺服器系統上安裝多個虛擬機器，請使用 <command>virt-install</command> 指令行工具。<command>virt-install</command> 支援多種安裝案例；下面概述了透過 VNC 和 PXE 開機進行的遠端安裝案例。如需有關 <command>virt-install</command> 的詳細資訊，請參閱<xref linkend="sec.libvirt.inst.virt-install"/>。
  </para>
  <para>
   依<xref linkend="sec.deployment.remoteinst.scenario.vncpxe"/>中所述，準備一個包含安裝來源的儲存庫，以及啟用了 PXE 開機的目標系統。
  </para>
  <para>
   在指令行中，輸入如下指令 (根據您的需要和硬體情況調整選項)：
  </para>

<screen>virt-install --name server_sle12 --memory 4096 --vcpus=2 --pxe \
--graphics vnc --os-variant sles11 \
--disk pool=default,size=3000,format=qcow2,allocation=1G,bus=virtio \
-w mac=<replaceable>mac_address</replaceable>,model=spapr-vlan</screen>
  <para>
   它將使用 VNC 圖形，並自動啟動圖形用戶端。
  </para>
 </sect2>
</sect1>
