<?xml version="1.0" encoding="UTF-8"?>
<glossdiv xmlns="http://docbook.org/ns/docbook" xmlns:xi="http://www.w3.org/2001/XInclude" xmlns:xlink="http://www.w3.org/1999/xlink" xml:base="vt_acronyms.xml" version="5.0" xml:id="gloss-vt-acronym">
 <title>缩写词</title>
 <info>
      <dm:docmanager xmlns:dm="urn:x-suse:ns:docmanager">
        <dm:bugtracker>
        </dm:bugtracker>
	<dm:translation>yes</dm:translation>
      </dm:docmanager>
    </info>
    <glossentry xml:id="gloss-vt-acpi"><glossterm>ACPI</glossterm>
  <glossdef>
   <para>
    高级配置和电源接口 (ACPI) 规范为操作系统的设备配置和电源管理提供了开放的标准。
   </para>
  </glossdef>
 </glossentry>
 <glossentry xml:id="gloss-vt-acronym-aer"><glossterm>AER</glossterm>
  <glossdef>
   <para>
    高级错误报告
   </para>
   <para>
    AER 是 PCI Express 规范提供的一项功能，用于报告 PCI 错误并在发生其中某些错误后进行恢复。
   </para>
  </glossdef>
 </glossentry>
 <glossentry xml:id="gloss-vt-apic"><glossterm>APIC</glossterm>
  <glossdef>
   <para>
    高级可编程中断控制器 (APIC) 是一个中断控制器系列。
   </para>
  </glossdef>
 </glossentry>
 <glossentry xml:id="gloss-xmtoxl-vt-bdf"><glossterm>BDF</glossterm>
  <glossdef>
   <para>
    总线:设备:功能
   </para>
   <para>
    用于简要描述 PCI 和 PCIe 设备的表示法。
   </para>
  </glossdef>
 </glossentry>
 <glossentry xml:id="gloss-vt-acronym-cg"><glossterm>CG</glossterm>
  <glossdef>
   <para>
    控制组
   </para>
   <para>
    用于限制、统计和隔离资源（CPU、内存、磁盘 I/O 等）使用量的功能。
   </para>
  </glossdef>
 </glossentry>
 <glossentry xml:id="gloss-xmtoxl-vt-edf"><glossterm>EDF</glossterm>
  <glossdef>
   <para>
    最早截止期限优先
   </para>
   <para>
    此调度程序以直观方式提供加权 CPU 共享，并使用实时算法来提供时间上的保障。
   </para>
  </glossdef>
 </glossentry>
 <glossentry xml:id="gloss-vt-acronym-ept"><glossterm>EPT</glossterm>
  <glossdef>
   <para>
    扩展页表
   </para>
   <para>
    虚拟化环境中的性能与本机环境非常接近。不过，虚拟化确实会产生一定的开销。这些开销源自 CPU、<xref linkend="gloss-vt-acronym-mmu"/> 和 I/O 设备的虚拟化。在一些新款 x86 处理器中，AMD 和 Intel 已开始提供硬件扩展来帮助弥补这种性能差距。2006 年，这两家供应商推出了采用 AMD-Virtualization (AMD-V) 和 Intel® VT-x 技术的第一代 x86 虚拟化硬件支持。最近，Intel 推出了其第二代硬件支持，其中整合了称作扩展页表 (EPT) 的 MMU 虚拟化。与使用影子分页技术进行 <xref linkend="gloss-vt-acronym-mmu"/> 虚拟化相比，支持 EPT 的系统可以提升性能。如果工作负载不多，EPT 会增加内存访问延迟，这个代价可以通过在 Guest 和超级管理程序中有效使用大页来降低。
   </para>
  </glossdef>
 </glossentry>
 <glossentry xml:id="gloss-xmtoxl-vt-flask"><glossterm>FLASK</glossterm>
  <glossdef>
   <para>
    Flux 高级安全内核
   </para>
   <para>
    Xen 通过一个称为 FLASK 的安全体系结构，使用同名的模块来实现某种类型的强制访问控制。
   </para>
  </glossdef>
 </glossentry>
 <glossentry xml:id="gloss-vt-acronym-hap"><glossterm>HAP</glossterm>
  <glossdef>
   <para>
    高保证平台
   </para>
   <para>
    HAP 结合了硬件和软件技术来提高工作站与网络安全性。
   </para>
  </glossdef>
 </glossentry>
 <glossentry xml:id="gloss-vt-acronym-hvm"><glossterm>HVM</glossterm>
  <glossdef>
   <para>
    硬件虚拟机（Xen 通常这样称呼）。
   </para>
  </glossdef>
 </glossentry>
 <glossentry xml:id="gloss-vt-acronym-iommu"><glossterm>IOMMU</glossterm>
  <glossdef>
   <para>
    输入/输出内存管理单元
   </para>
   <para>
    IOMMU（AMD* 技术）是内存管理单元 (<xref linkend="gloss-vt-acronym-mmu"/>)，可将支持直接内存访问 (DMA) 的 I/O 总线连接到主内存。
   </para>
  </glossdef>
 </glossentry>
 <glossentry xml:id="gloss-vt-acronym-ksm"><glossterm>KSM</glossterm>
  <glossdef>
   <para>
    内核同页合并
   </para>
   <para>
    KSM 可用于在 Guest 之间自动共享相同的内存页，以节省主机内存。KVM 经优化后可以使用 KSM（如果已在 VM 主机服务器上启用）。
   </para>
  </glossdef>
 </glossentry>
 <glossentry xml:id="gloss-vt-acronym-mmu"><glossterm>MMU</glossterm>
  <glossdef>
   <para>
    内存管理单元
   </para>
   <para>
    一个计算机硬件组件，负责处理 CPU 的内存访问请求。其功能包括虚拟地址到物理地址的转换（即虚拟内存管理）、内存保护、缓存控制、总线仲裁，在较为简单的计算机体系结构（尤其是 8 位系统）中，负责储存体切换。
   </para>
  </glossdef>
 </glossentry>
 <glossentry xml:id="gloss-vt-acronym-pae"><glossterm>PAE</glossterm>
  <glossdef>
   <para>
    物理地址扩展
   </para>
   <para>
    32 位 x86 操作系统使用物理地址扩展 (PAE) 模式来实现 4 GB 以上物理内存的寻址。在 PAE 模式下，页表项 (PTE) 的大小为 64 位。
   </para>
  </glossdef>
 </glossentry>
 <glossentry xml:id="gloss-vt-acronym-pcid"><glossterm>PCID</glossterm>
  <glossdef>
   <para>
    进程环境标识符
   </para>
   <para>
    逻辑处理器可通过这些标识符缓存多个线性地址空间的信息，这样当软件切换到其他线性地址空间时，处理器能够保留缓存的信息。INVPCID 指令用于进行精细的 <xref linkend="gloss-vt-acronym-tlb"/> 刷新，这对于内核会有所助益。
   </para>
  </glossdef>
 </glossentry>
 <glossentry xml:id="gloss-vt-acronym-pcie"><glossterm>PCIe</glossterm>
  <glossdef>
   <para>
    高速外设组件互连
   </para>
   <para>
    PCIe 用来替代旧式 PCI、PCI-X 和 AGP 总线标准。PCIe 融入了大量改进，包括更高的最大系统总线吞吐量、更低的 I/O 脚数，以及更小的物理占用空间。此外，它还提供更详细的错误检测和报告机制 (<xref linkend="gloss-vt-acronym-aer"/>)，以及本机热插拔功能。它还向后兼容 PCI。
   </para>
  </glossdef>
 </glossentry>
 <glossentry xml:id="gloss-vt-acronym-pse-pse36"><glossterm>PSE 和 PSE36</glossterm>
  <glossdef>
   <para>
    扩展页大小
   </para>
   <para>
    PSE 是指 x86 处理器的一项功能，允许页大于传统的 4 KiB 大小。PSE-36 功能在普通 10 位的基础上再额外提供 4 位，这些额外的位在指向大页的页目录项中使用。这样，便可以将大页放到 36 位地址空间中。
   </para>
  </glossdef>
 </glossentry>
 <glossentry xml:id="gloss-vt-acronym-pt"><glossterm>PT</glossterm>
  <glossdef>
   <para>
    页表
   </para>
   <para>
    页表是计算机操作系统中的虚拟内存系统用来储存虚拟地址与物理地址之间的映射的数据结构。虚拟地址是访问进程特有的地址。物理地址是硬件 (RAM) 特有的地址。
   </para>
  </glossdef>
 </glossentry>
 <glossentry xml:id="gloss-vt-acronym-qxl"><glossterm>QXL</glossterm>
  <glossdef>
   <para>
    QXL 是虚拟化环境的 cirrus VGA 帧缓冲 (8M) 驱动程序。
   </para>
  </glossdef>
 </glossentry>
 <glossentry xml:id="gloss-vt-acronym-rvi-npt"><glossterm>RVI 或 NPT</glossterm>
  <glossdef>
   <para>
    快速虚拟化索引、嵌套式页表
   </para>
   <para>
    适用于处理器内存管理单元 (<xref linkend="gloss-vt-acronym-mmu"/>) 的 AMD 第二代硬件辅助虚拟化技术。
   </para>
  </glossdef>
 </glossentry>
 <glossentry xml:id="gloss-vt-acronym-sata"><glossterm>SATA</glossterm>
  <glossdef>
   <para>
    串行 ATA
   </para>
   <para>
    SATA 是一个计算机总线接口，可将主机总线适配器连接到硬盘和光驱等大容量储存设备。
   </para>
  </glossdef>
 </glossentry>
 <glossentry xml:id="gloss-vt-acronym-seccomp2-based-sandboxing"><glossterm>基于 Seccomp2 的沙箱</glossterm>
  <glossdef>
   <para>
    为了增强恶意行为防范能力而只允许使用预先确定的系统调用的沙箱环境。
   </para>
  </glossdef>
 </glossentry>
 <glossentry xml:id="gloss-vt-acronym-smep"><glossterm>SMEP</glossterm>
  <glossdef>
   <para>
    监督模式执行保护
   </para>
   <para>
    用于防止 Xen 超级管理程序执行用户模式页，使通过应用程序恶意利用超级管理程序的许多企图更难以实现。
   </para>
  </glossdef>
 </glossentry>
 <glossentry xml:id="gloss-vt-acronym-spice"><glossterm>SPICE</glossterm>
  <glossdef>
   <para>
    适用于独立计算环境的简单协议
   </para>
  </glossdef>
 </glossentry>
 <glossentry xml:id="gloss-xmtoxl-vt-sxp"><glossterm>SXP</glossterm>
  <glossdef>
   <para>
    SXP 文件是 Xen 配置文件。
   </para>
  </glossdef>
 </glossentry>
 <glossentry xml:id="gloss-vt-acronym-tcg"><glossterm>TCG</glossterm>
  <glossdef>
   <para>
    微代码生成器
   </para>
   <para>
    模拟指令，而不是由 CPU 执行指令。
   </para>
  </glossdef>
 </glossentry>
 <glossentry xml:id="gloss-vt-acronym-thp"><glossterm>THP</glossterm>
  <glossdef>
   <para>
    透明大页
   </para>
   <para>
    此功能可让 CPU 使用大于默认 4 KB 的页进行内存寻址。这有助于减少内存消耗量和 CPU 缓存用量。KVM 经优化后可以通过 madvise 和机会性方法使用 THP（如果已在 VM 主机服务器上启用）。
   </para>
  </glossdef>
 </glossentry>
 <glossentry xml:id="gloss-vt-acronym-tlb"><glossterm>TLB</glossterm>
  <glossdef>
   <para>
    转换后援缓冲区
   </para>
   <para>
    TLB 是内存管理硬件用来提升虚拟地址转换速度的缓存。所有最新的台式机、笔记本电脑和服务器处理器都使用 TLB 来映射虚拟和物理地址空间，在任何使用虚拟内存的硬件中，几乎都会用到 TLB。
   </para>
  </glossdef>
 </glossentry>
 <glossentry xml:id="gloss-vt-acronym-vcpu"><glossterm>VCPU</glossterm>
  <glossdef>
   <para>
    一个调度实体，包含虚拟化 CPU 的每种状态。
   </para>
  </glossdef>
 </glossentry>
 <glossentry xml:id="gloss-vt-acronym-vdi"><glossterm>VDI</glossterm>
  <glossdef>
   <para>
    虚拟桌面基础结构
   </para>
  </glossdef>
 </glossentry>
 <glossentry xml:id="gloss-vt-acronym-vfio"><glossterm>VFIO</glossterm>
  <glossdef>
   <para>
    从内核 v3.6 开始，推出了一种从用户空间访问 PCI 设备的新方法，该方法称为 VFIO。
   </para>
  </glossdef>
 </glossentry>
 <glossentry xml:id="gloss-vt-acronym-vhs"><glossterm>VHS</glossterm>
  <glossdef>
   <para>
    虚拟化主机服务器
   </para>
  </glossdef>
 </glossentry>
 <glossentry xml:id="gloss-vt-acronym-vmcs"><glossterm>VMCS</glossterm>
  <glossdef>
   <para>
    虚拟机控制结构
   </para>
   <para>
    VMX 非 root 操作和 VMX 转换由一个称为虚拟机控制结构 (VMCS) 的数据结构来控制。VMCS 访问通过称为 VMCS 指针（每个逻辑处理器一个）的处理器状态组件来管理。VMCS 指针的值是 VMCS 的 64 位地址。通过 VMPTRST 和 VMPTRLD 指令来读取和写入 VMCS 指针。<xref linkend="gloss-vt-acronym-hypervisor-vmm"/> 使用 VMREAD、VMWRITE 和 VMCLEAR 指令来配置 VMCS。<xref linkend="gloss-vt-acronym-hypervisor-vmm"/> 可对它支持的每个虚拟机使用不同的 VMCS。如果虚拟机具有多个逻辑处理器（虚拟处理器），<xref linkend="gloss-vt-acronym-hypervisor-vmm"/> 可对每个虚拟处理器使用不同的 VMCS。
   </para>
  </glossdef>
 </glossentry>
 <glossentry xml:id="gloss-vt-acronym-vmdq"><glossterm>VMDq</glossterm>
  <glossdef>
   <para>
    虚拟机设备队列
   </para>
   <para>
    多队列网络适配器可在硬件级别支持多个 VM，它们能使不同的包队列关联到不同的托管 VM（通过 VM 的 IP 地址进行关联）。
   </para>
  </glossdef>
 </glossentry>
 <glossentry xml:id="gloss-vt-acronym-hypervisor-vmm"><glossterm>VMM</glossterm>
  <glossdef>
   <para>
    虚拟机监视器（超级管理程序）
   </para>
   <para>
    当处理器遇到与超级管理程序 (<xref linkend="gloss-vt-acronym-hypervisor-vmm"/>) 相关的指令或事件时，它会退出 Guest 模式并回到 VMM。VMM 以远低于本机的速度模拟该指令或另一事件，然后返回到 Guest 模式。Guest 模式与 VMM 之间的来回转换属于高延迟操作，在此期间，Guest 执行会完全停滞。
   </para>
  </glossdef>
 </glossentry>
 <glossentry xml:id="gloss-vt-acronym-vmroot"><glossterm>VM root</glossterm>
  <glossdef>
   <para>
    <xref linkend="gloss-vt-acronym-hypervisor-vmm"/> 以 <xref linkend="gloss-vt-acronym-vmx"/> root 操作运行，Guest 软件以 <xref linkend="gloss-vt-acronym-vmx"/> 非 root 操作运行。<xref linkend="gloss-vt-acronym-vmx"/> root 操作与 <xref linkend="gloss-vt-acronym-vmx"/> 非 root 操作之间的转换称为 <xref linkend="gloss-vt-acronym-vmx"/> 转换。
   </para>
  </glossdef>
 </glossentry>
 <glossentry xml:id="gloss-vt-acronym-vmx"><glossterm>VMX</glossterm>
  <glossdef>
   <para>
    虚拟机扩展
   </para>
  </glossdef>
 </glossentry>
 <glossentry xml:id="gloss-vt-acronym-vpid"><glossterm>VPID</glossterm>
  <glossdef>
   <para>
    新的 <xref linkend="gloss-vt-acronym-tlb"/> 软件控制支持（利用 VPID，您只需进行少量的 <xref linkend="gloss-vt-acronym-hypervisor-vmm"/> 开发，就能提升 <xref linkend="gloss-vt-acronym-tlb"/> 性能）。
   </para>
  </glossdef>
 </glossentry>
 <glossentry xml:id="gloss-vt-acronym-vtd"><glossterm>VT-d</glossterm>
  <glossdef>
   <para>
    定向 I/O 虚拟化技术
   </para>
   <para>
    类似于 <link xlink:href="https://software.intel.com/en-us/articles/intel-virtualization-technology-for-directed-io-vt-d-enhancing-intel-platforms-for-efficient-virtualization-of-io-devices">Intel* 的 <xref linkend="gloss-vt-acronym-iommu"/></link>。
   </para>
  </glossdef>
 </glossentry>
 <glossentry xml:id="gloss-vt-acronym-vtpm"><glossterm>vTPM</glossterm>
  <glossdef>
   <para>
    用于通过可信计算为 Guest 建立端到端完整性的组件。
   </para>
  </glossdef>
 </glossentry>
</glossdiv>
